LICENSE
MANIFEST.in
README.md
requirements.txt
setup.py
ct_api_gateway_deployer/__init__.py
ct_api_gateway_deployer/__main__.py
ct_api_gateway_deployer/create_api.py
ct_api_gateway_deployer/flask_tools.py
ct_api_gateway_deployer/version.py
ct_api_gateway_deployer.egg-info/PKG-INFO
ct_api_gateway_deployer.egg-info/SOURCES.txt
ct_api_gateway_deployer.egg-info/dependency_links.txt
ct_api_gateway_deployer.egg-info/requires.txt
ct_api_gateway_deployer.egg-info/top_level.txt
ct_api_gateway_deployer/src/__init__.py
ct_api_gateway_deployer/src/open_api_parser.py
ct_api_gateway_deployer/src/validator.py
ct_api_gateway_deployer/src/aws/__init__.py
ct_api_gateway_deployer/src/aws/aws_api_gateway.py
ct_api_gateway_deployer/src/aws/aws_client.py
ct_api_gateway_deployer/src/aws/aws_loader.py
ct_api_gateway_deployer/src/common/__init__.py
ct_api_gateway_deployer/src/common/abstract_exception.py
ct_api_gateway_deployer/src/common/utils.py
ct_api_gateway_deployer/src/common/exceptions/__init__.py
ct_api_gateway_deployer/src/common/exceptions/generic_exception.py