Metadata-Version: 2.1
Name: ct-api-gateway-deployer
Version: 1.1.3
Summary: Package to automatize the configuration of an Flask API REST application inside the AWS API Gateway.
Home-page: https://bitbucket.org/cinnecta/ct-api-gateway-deployer.git
Author: Cinnecta
Author-email: cinnecta.dev@gmail.com
License: UNKNOWN
Platform: UNKNOWN
Classifier: Programming Language :: Python :: 3
Classifier: License :: OSI Approved :: MIT License
Classifier: Operating System :: OS Independent
